calculator_toolkit/__init__.py
calculator_toolkit/shapes.py
calculator_toolkit-0.1.0.dist-info/LICENSE
calculator_toolkit-0.1.0.dist-info/METADATA
calculator_toolkit-0.1.0.dist-info/WHEEL
calculator_toolkit-0.1.0.dist-info/top_level.txt
calculator_toolkit-0.1.0.dist-info/RECORD
